Metadata-Version: 2.1
Name: bo22-dsnd-probability-distributions
Version: 1.0
Summary: Gaussian and Binomial distributions
Home-page: UNKNOWN
Author-email: bolbor22@gmail.com
License: UNKNOWN
Platform: UNKNOWN
